MANIFEST.in
Makefile
README.rst
setup.cfg
setup.py
phantomas/__init__.py
phantomas/client.py
phantomas/errors.py
phantomas/results.py
phantomas/utils.py
phantomas.egg-info/PKG-INFO
phantomas.egg-info/SOURCES.txt
phantomas.egg-info/dependency_links.txt
phantomas.egg-info/requires.txt
phantomas.egg-info/top_level.txt
tests/__init__.py
tests/test_format_args.py
tests/test_phantomas.py
tests/test_phantomas_run.py
tests/test_results.py