Metadata-Version: 1.1
Name: phantomas
Version: 0.2.3
Summary: Python module for easy integration with phantomas
Home-page: https://github.com/macbre/phantomas-python
Author: Maciej Brencz
Author-email: maciej.brencz@gmail.com
License: MIT
Keywords: high performance web sites,metrics,monitoring,phantomas,phantomjs,web development,webperf
Platform: UNKNOWN
Classifier: Development Status :: 4 - Beta
Classifier: Environment :: Console
Classifier: Intended Audience :: Developers
Classifier: License :: OSI Approved :: MIT License
Classifier: Topic :: Internet :: WWW/HTTP
Classifier: Programming Language :: Python :: 2
Classifier: Programming Language :: Python :: 2.6
Classifier: Programming Language :: Python :: 2.7
Classifier: Programming Language :: Python :: 3
Classifier: Programming Language :: Python :: 3.2
Classifier: Programming Language :: Python :: 3.3
Classifier: Programming Language :: Python :: 3.4
